pydep_extractor/__main__.py
pydep_extractor/extractor.py
pydep_extractor-0.1.0.dist-info/LICENSE
pydep_extractor-0.1.0.dist-info/METADATA
pydep_extractor-0.1.0.dist-info/WHEEL
pydep_extractor-0.1.0.dist-info/top_level.txt
pydep_extractor-0.1.0.dist-info/RECORD
