Metadata-Version: 2.1
Name: pydep-extractor
Version: 0.1.0
Summary: Extractor for python dependencies form pyproject.toml file and create requirements.txt file to be used in docker image builds
Author: partun
Project-URL: Bug Tracker, https://github.com/partun/pydep-extractor/issues
Project-URL: Homepage, https://github.com/partun/pydep-extractor
Classifier: Programming Language :: Python :: 3
Classifier: License :: OSI Approved :: MIT License
Classifier: Operating System :: OS Independent
Requires-Python: >=3.8
License-File: LICENSE
Requires-Dist: toml >=0.10.2
Provides-Extra: dev
Requires-Dist: pyproject-flake8 ==5.0.4 ; extra == 'dev'
Requires-Dist: black[d] ==22.10.0 ; extra == 'dev'
Requires-Dist: mypy ==0.982 ; extra == 'dev'
Requires-Dist: pre-commit ==2.20.0 ; extra == 'dev'
Requires-Dist: pytest ==7.4.3 ; extra == 'dev'
Provides-Extra: publish
Requires-Dist: build ; extra == 'publish'
Requires-Dist: twine ; extra == 'publish'
